ocpi/__init__.py
ocpi/exceptions.py
ocpi/managers.py
ocpi/models/__init__.py
ocpi/models/cdrs.py
ocpi/models/charging_profiles.py
ocpi/models/commands.py
ocpi/models/credentials.py
ocpi/models/location.py
ocpi/models/parking.py
ocpi/models/reservation.py
ocpi/models/sessions.py
ocpi/models/tariffs.py
ocpi/models/tokens.py
ocpi/models/types.py
ocpi/models/version.py
ocpi/namespaces/__init__.py
ocpi/namespaces/cdrs.py
ocpi/namespaces/charging_profiles.py
ocpi/namespaces/commands.py
ocpi/namespaces/credentials.py
ocpi/namespaces/locations.py
ocpi/namespaces/parking.py
ocpi/namespaces/reservation.py
ocpi/namespaces/sessions.py
ocpi/namespaces/tariffs.py
ocpi/namespaces/tokens.py
ocpi/namespaces/versions.py
python_ocpi-0.3.1.dist-info/LICENSE
python_ocpi-0.3.1.dist-info/WHEEL
python_ocpi-0.3.1.dist-info/METADATA
python_ocpi-0.3.1.dist-info/RECORD
