Metadata-Version: 2.1
Name: python-ocpi
Version: 0.3.1
Summary: Python library for the Open Charge Point Interface (OCPI)
Home-page: https://github.com/NOWUM/pyocpi
License: MIT
Keywords: ev,charging,OpenAPI,Swagger,REST
Author: Florian Maurer
Author-email: maurer@fh-aachen.de
Requires-Python: >=3.7,<4.0
Classifier: Development Status :: 5 - Production/Stable
Classifier: Intended Audience :: Developers
Classifier: License :: OSI Approved :: MIT License
Classifier: Operating System :: OS Independent
Classifier: Programming Language :: Python :: 3
Classifier: Programming Language :: Python :: 3.7
Classifier: Programming Language :: Python :: 3.8
Classifier: Programming Language :: Python :: 3.9
Classifier: Programming Language :: Python :: 3.10
Classifier: Programming Language :: Python :: 3.11
Classifier: Topic :: Scientific/Engineering :: Interface Engine/Protocol Translator
Classifier: Topic :: Software Development :: Libraries :: Python Modules
Requires-Dist: flask
Requires-Dist: flask-restx (>=0.5.0)
Requires-Dist: importlib_metadata (>=4.0.0); python_version < "3.8"
Project-URL: Repository, https://github.com/NOWUM/pyocpi
